ppml/__init__.py
ppml/dp.py
ppml-0.1.2.dist-info/LICENSE
ppml-0.1.2.dist-info/METADATA
ppml-0.1.2.dist-info/WHEEL
ppml-0.1.2.dist-info/top_level.txt
ppml-0.1.2.dist-info/RECORD
