Metadata-Version: 2.1
Name: ppml
Version: 0.1.2
Summary: A privacy-preserving machine learning package
Home-page: https://github.com/BagelNetwork/ppml
Author: Bidhan Roy
Author-email: bidhan@bagel.net
Classifier: Development Status :: 3 - Alpha
Classifier: Intended Audience :: Developers
Classifier: License :: OSI Approved :: MIT License
Classifier: Operating System :: OS Independent
Classifier: Programming Language :: Python :: 3
Classifier: Programming Language :: Python :: 3.7
Classifier: Programming Language :: Python :: 3.8
Classifier: Programming Language :: Python :: 3.9
Requires-Python: >=3.7
License-File: LICENSE
Requires-Dist: torch>=1.8.0
Requires-Dist: torchvision>=0.9.0
Requires-Dist: opacus>=1.0.0
Requires-Dist: numpy
Requires-Dist: Pillow
Requires-Dist: tqdm
